README.rst
setup.py
django_uuid_upload/__init__.py
django_uuid_upload.egg-info/PKG-INFO
django_uuid_upload.egg-info/SOURCES.txt
django_uuid_upload.egg-info/dependency_links.txt
django_uuid_upload.egg-info/requires.txt
django_uuid_upload.egg-info/top_level.txt