Metadata-Version: 1.0
Name: django-uuid-upload
Version: 0.0.1
Summary: Store Django uploaded files as {uuid}.jpg or {uuid}/original.jpg
Home-page: https://github.com/IlyaSemenov/django-uuid-upload
Author: Ilya Semenov
Author-email: ilya@semenov.co
License: BSD
Platform: UNKNOWN
